{"name":"Login Success","id":"register;login-success","testSteps":[{"number":1,"description":"Given I am on the register page","duration":55,"startTime":"2021-12-12T18:05:58.566+07:00[Asia/Bangkok]","result":"SUCCESS","precondition":false,"level":0},{"number":2,"description":"When I enter my name,email,password,phone correctly","duration":2,"startTime":"2021-12-12T18:05:58.627+07:00[Asia/Bangkok]","result":"SUCCESS","precondition":false,"level":0},{"number":3,"description":"And I click \u0027Submit\u0027 buttons","duration":4,"startTime":"2021-12-12T18:05:58.630+07:00[Asia/Bangkok]","result":"SUCCESS","precondition":false,"level":0},{"number":4,"description":"Then I am taken to the Home_Page","duration":3,"startTime":"2021-12-12T18:05:58.634+07:00[Asia/Bangkok]","result":"SUCCESS","precondition":false,"level":0}],"userStory":{"id":"register","storyName":"Register","path":"file:src/test/resources/Features/Account/register.feature","narrative":"  As a Rentz Web API\n  I want to see my account\n  So that I can edit my account","type":"feature"},"featureTag":{"name":"Account/Register","type":"feature","displayName":"Account/Register"},"title":"Login Success","tags":[{"name":"Account/Register","type":"feature","displayName":"Register"},{"name":"Account","type":"capability","displayName":"Account"},{"name":"Register","type":"tag","displayName":"Register"}],"startTime":"2021-12-12T18:05:58.433+07:00[Asia/Bangkok]","duration":206,"projectKey":"","isManualTestingUpToDate":false,"manual":false,"testSource":"Cucumber","result":"SUCCESS"}